ldmud_asyncio/__init__.py
ldmud_asyncio-0.0.4.dist-info/LICENSE
ldmud_asyncio-0.0.4.dist-info/METADATA
ldmud_asyncio-0.0.4.dist-info/WHEEL
ldmud_asyncio-0.0.4.dist-info/top_level.txt
ldmud_asyncio-0.0.4.dist-info/RECORD
