Metadata-Version: 2.1
Name: ldmud-asyncio
Version: 0.0.4
Summary: Python asynchronous I/O package for LDMud
Home-page: https://github.com/ldmud/python-asyncio
Author: LDMud Team
Author-email: ldmud-dev@UNItopia.DE
License: UNKNOWN
Platform: UNKNOWN
Classifier: Programming Language :: Python :: 3
Classifier: License :: OSI Approved :: ISC License (ISCL)
Classifier: Operating System :: OS Independent
Requires-Python: >=3.5
